{
	"info": {
		"_postman_id": "c84c794c-0294-4576-90fe-963b017f8b77",
		"name": "AgroNET",
		"schema": "https://schema.getpostman.com/json/collection/v2.1.0/collection.json",
		"_exporter_id": "32453971"
	},
	"item": [
		{
			"name": "User",
			"item": [
				{
					"name": "Get user",
					"request": {
						"method": "GET",
						"header": [],
						"url": {
							"raw": "{{url}}/users",
							"host": [
								"{{url}}"
							],
							"path": [
								"users"
							]
						}
					},
					"response": []
				},
				{
					"name": "Create user",
					"request": {
						"method": "POST",
						"header": [],
						"body": {
							"mode": "raw",
							"raw": "{\n    \"name\": \"Jorge\"\n}",
							"options": {
								"raw": {
									"language": "json"
								}
							}
						},
						"url": {
							"raw": "{{url}}/users",
							"host": [
								"{{url}}"
							],
							"path": [
								"users"
							]
						}
					},
					"response": []
				}
			]
		},
		{
			"name": "Hello world",
			"request": {
				"method": "GET",
				"header": [],
				"url": {
					"raw": "{{url}}",
					"host": [
						"{{url}}"
					]
				}
			},
			"response": []
		}
	],
	"event": [
		{
			"listen": "prerequest",
			"script": {
				"type": "text/javascript",
				"packages": {},
				"exec": [
					""
				]
			}
		},
		{
			"listen": "test",
			"script": {
				"type": "text/javascript",
				"packages": {},
				"exec": [
					""
				]
			}
		}
	],
	"variable": [
		{
			"key": "url",
			"value": "http://localhost:3000/",
			"type": "string"
		}
	]
}